source_hardcoded_records/__init__.py
source_hardcoded_records/run.py
source_hardcoded_records/schemas/customers.json
source_hardcoded_records/schemas/dummy_fields.json
source_hardcoded_records/schemas/products.json
source_hardcoded_records/source.py
source_hardcoded_records/spec.json
source_hardcoded_records/streams.py
airbyte_source_hardcoded_records-0.0.46.dist-info/METADATA
airbyte_source_hardcoded_records-0.0.46.dist-info/WHEEL
airbyte_source_hardcoded_records-0.0.46.dist-info/entry_points.txt
airbyte_source_hardcoded_records-0.0.46.dist-info/RECORD
