Metadata-Version: 2.1
Name: airbyte-source-hardcoded-records
Version: 0.0.46
Summary: Source implementation for hardcoded records.
Home-page: https://airbyte.com
License: ELv2
Author: Airbyte
Author-email: evan@airbyte.io
Requires-Python: >=3.11,<3.13
Classifier: License :: Other/Proprietary License
Classifier: Programming Language :: Python :: 3
Classifier: Programming Language :: Python :: 3.11
Classifier: Programming Language :: Python :: 3.12
Requires-Dist: airbyte-cdk (==6.46.0)
Project-URL: Documentation, https://docs.airbyte.com/integrations/sources/hardcoded-records
Project-URL: Repository, https://github.com/airbytehq/airbyte
